{
    "Test Deck":{
        "Blue-Eyes White Dragon":3,
        "Dark Magician":3,
        "Red-Eyes Black Dragon":3,
        "Elemental HERO Burstinatrix":3,
        "Elemental HERO Avian":3,
        "Left Arm of the Forbidden One":1,
        "Right Leg of the Forbidden One":1,
        "Left Leg of the Forbidden One":1,
        "Right Arm of the Forbidden One":1,
        "Dark Magician Girl":2,
        "Cyber Dragon":3,
        "Exodia the Forbidden One":1,
        "Kuriboh":3,
        "Winged Kuriboh":3,
        "Pot of Greed":3,
        "Mystical Moon":3,
        "Mirror Force":3
    }
}